sml-mqtt-bridge.py
sml-mqtt-bridge.service
test_asyncio.py
sml/__init__.py
sml/asyncio.py
pysml-0.1.5.dist-info/LICENSE
pysml-0.1.5.dist-info/METADATA
pysml-0.1.5.dist-info/WHEEL
pysml-0.1.5.dist-info/RECORD
