Metadata-Version: 2.1
Name: pysml
Version: 0.1.5
Summary: Python library for EDL21 smart meters using Smart Message Language (SML)
License: MIT
Author: Andreas Oberritter
Author-email: obi@saftware.de
Requires-Python: >=3.11,<4.0
Classifier: License :: OSI Approved :: MIT License
Classifier: Programming Language :: Python :: 3
Classifier: Programming Language :: Python :: 3.11
Classifier: Programming Language :: Python :: 3.12
Requires-Dist: aiohttp (>=3.8.4,<4.0.0)
Requires-Dist: bitstring (>=3.1)
Requires-Dist: pyserial-asyncio-fast (>=0.16)
